pyfin/__init__.py
pyfin/core.py
pyfin/data.py
pyfin/utils.py
pyfin-1.0.0a1.dist-info/DESCRIPTION.rst
pyfin-1.0.0a1.dist-info/METADATA
pyfin-1.0.0a1.dist-info/RECORD
pyfin-1.0.0a1.dist-info/WHEEL
pyfin-1.0.0a1.dist-info/metadata.json
pyfin-1.0.0a1.dist-info/top_level.txt
